odoo/addons/account_financial_discount/README.rst
odoo/addons/account_financial_discount/__init__.py
odoo/addons/account_financial_discount/__manifest__.py
odoo/addons/account_financial_discount/i18n/account_financial_discount.pot
odoo/addons/account_financial_discount/i18n/es.po
odoo/addons/account_financial_discount/i18n/it.po
odoo/addons/account_financial_discount/models/__init__.py
odoo/addons/account_financial_discount/models/account_move.py
odoo/addons/account_financial_discount/models/account_move_line.py
odoo/addons/account_financial_discount/models/account_payment_term.py
odoo/addons/account_financial_discount/models/account_reconcile_model.py
odoo/addons/account_financial_discount/models/res_company.py
odoo/addons/account_financial_discount/models/res_config_settings.py
odoo/addons/account_financial_discount/readme/CONFIGURE.rst
odoo/addons/account_financial_discount/readme/CONTRIBUTORS.rst
odoo/addons/account_financial_discount/readme/DESCRIPTION.rst
odoo/addons/account_financial_discount/readme/ROADMAP.rst
odoo/addons/account_financial_discount/readme/USAGE.rst
odoo/addons/account_financial_discount/static/description/icon.png
odoo/addons/account_financial_discount/static/description/index.html
odoo/addons/account_financial_discount/tests/__init__.py
odoo/addons/account_financial_discount/tests/common.py
odoo/addons/account_financial_discount/tests/test_financial_discount_manual_payment.py
odoo/addons/account_financial_discount/tests/test_financial_discount_reconciliation.py
odoo/addons/account_financial_discount/tests/test_payment_term.py
odoo/addons/account_financial_discount/views/account_move.xml
odoo/addons/account_financial_discount/views/account_reconcile_model.xml
odoo/addons/account_financial_discount/views/payment_receipt.xml
odoo/addons/account_financial_discount/views/payment_term_form.xml
odoo/addons/account_financial_discount/views/res_config_settings.xml
odoo/addons/account_financial_discount/wizard/__init__.py
odoo14_addon_account_financial_discount-14.0.1.0.1.dist-info/METADATA
odoo14_addon_account_financial_discount-14.0.1.0.1.dist-info/WHEEL
odoo14_addon_account_financial_discount-14.0.1.0.1.dist-info/top_level.txt
odoo14_addon_account_financial_discount-14.0.1.0.1.dist-info/RECORD
